open_samus_returns_rando/__init__.py
open_samus_returns_rando/__main__.py
open_samus_returns_rando/cli.py
open_samus_returns_rando/constants.py
open_samus_returns_rando/debug.py
open_samus_returns_rando/exefs_patches.py
open_samus_returns_rando/logger.py
open_samus_returns_rando/lua_editor.py
open_samus_returns_rando/patch_util.py
open_samus_returns_rando/patcher_editor.py
open_samus_returns_rando/py.typed
open_samus_returns_rando/samus_returns_patcher.py
open_samus_returns_rando/validator_with_default.py
open_samus_returns_rando/version.py
open_samus_returns_rando/__pyinstaller/__init__.py
open_samus_returns_rando/__pyinstaller/hook-open_samus_returns_rando.py
open_samus_returns_rando/files/__init__.py
open_samus_returns_rando/files/schema.json
open_samus_returns_rando/files/custom/arachnus.lua
open_samus_returns_rando/files/custom/doors.lua
open_samus_returns_rando/files/custom/guilib.lua
open_samus_returns_rando/files/custom/queue.lua
open_samus_returns_rando/files/custom/randoapi.lua
open_samus_returns_rando/files/custom/room_names.lua
open_samus_returns_rando/files/custom/savestation.lua
open_samus_returns_rando/files/custom/scenario.lua
open_samus_returns_rando/files/custom/ship.lua
open_samus_returns_rando/files/custom/sprites_splashes.lua
open_samus_returns_rando/files/custom/sprites_texturehud.lua
open_samus_returns_rando/files/exefs_patches/code.ips
open_samus_returns_rando/files/exefs_patches/exheader.ips
open_samus_returns_rando/files/levels/s000_surface.lua
open_samus_returns_rando/files/levels/s010_area1.lua
open_samus_returns_rando/files/levels/s020_area2.lua
open_samus_returns_rando/files/levels/s025_area2b.lua
open_samus_returns_rando/files/levels/s028_area2c.lua
open_samus_returns_rando/files/levels/s030_area3.lua
open_samus_returns_rando/files/levels/s033_area3b.lua
open_samus_returns_rando/files/levels/s036_area3c.lua
open_samus_returns_rando/files/levels/s040_area4.lua
open_samus_returns_rando/files/levels/s050_area5.lua
open_samus_returns_rando-3.4.0.dist-info/licenses/LICENSE
open_samus_returns_rando-3.4.0.dist-info/METADATA
open_samus_returns_rando-3.4.0.dist-info/WHEEL
open_samus_returns_rando-3.4.0.dist-info/entry_points.txt
open_samus_returns_rando-3.4.0.dist-info/top_level.txt
open_samus_returns_rando-3.4.0.dist-info/RECORD
