Metadata-Version: 2.4
Name: open_samus_returns_rando
Version: 3.4.0
Summary: An open source randomizer patcher for Metroid: Samus Returns.
Project-URL: Homepage, https://github.com/randovania/open-samus-returns-rando
Classifier: License :: OSI Approved :: GNU General Public License v3 (GPLv3)
Classifier: Development Status :: 3 - Alpha
Classifier: Intended Audience :: Developers
Classifier: Programming Language :: Python :: 3.10
Requires-Python: >=3.10
License-File: LICENSE
Requires-Dist: mercury-engine-data-structures>=0.35.0
Requires-Dist: jsonschema>=4.0.0
Requires-Dist: ips.py>=0.1.2
Provides-Extra: typing
Requires-Dist: types-jsonschema; extra == "typing"
Requires-Dist: types-pyinstaller; extra == "typing"
Requires-Dist: mypy; extra == "typing"
Provides-Extra: test
Requires-Dist: pytest; extra == "test"
Dynamic: license-file
